.travis.yml
CHANGES.rst
MANIFEST.in
README.rst
development.ini
setup.cfg
setup.py
todo.txt
kotti_settings/__init__.py
kotti_settings/config.py
kotti_settings/events.py
kotti_settings/form.py
kotti_settings/settings.py
kotti_settings/testing.py
kotti_settings/util.py
kotti_settings/views.py
kotti_settings.egg-info/PKG-INFO
kotti_settings.egg-info/SOURCES.txt
kotti_settings.egg-info/dependency_links.txt
kotti_settings.egg-info/not-zip-safe
kotti_settings.egg-info/requires.txt
kotti_settings.egg-info/top_level.txt
kotti_settings/locale/README
kotti_settings/locale/kotti_settings.pot
kotti_settings/locale/de/LC_MESSAGES/kotti_settings.po
kotti_settings/locale/en/LC_MESSAGES/kotti_settings.po
kotti_settings/templates/settings.pt
kotti_settings/tests/__init__.py
kotti_settings/tests/__init__.pyc
kotti_settings/tests/conftest.py
kotti_settings/tests/conftest.pyc
kotti_settings/tests/test_app.py
kotti_settings/tests/test_browser.rst
kotti_settings/tests/test_configure.py
kotti_settings/tests/test_events.py
kotti_settings/tests/test_util.py
kotti_settings/tests/test_views.py
kotti_settings/tests/__pycache__/test_app.cpython-27-PYTEST.pyc
kotti_settings/tests/__pycache__/test_configure.cpython-27-PYTEST.pyc
kotti_settings/tests/__pycache__/test_events.cpython-27-PYTEST.pyc
kotti_settings/tests/__pycache__/test_util.cpython-27-PYTEST.pyc
kotti_settings/tests/__pycache__/test_views.cpython-27-PYTEST.pyc